dove/__init__.py
dove-0.0.1.dist-info/DESCRIPTION.rst
dove-0.0.1.dist-info/METADATA
dove-0.0.1.dist-info/RECORD
dove-0.0.1.dist-info/WHEEL
dove-0.0.1.dist-info/metadata.json
dove-0.0.1.dist-info/top_level.txt
