Metadata-Version: 2.0
Name: dove
Version: 0.0.1
Summary: A static blog with background management
Home-page: https://github.com/xiaojieluo/dove
Author: Luo Xiaojie
Author-email: xiaojieluoff@gmail.com
License: Apache License
